yta_multimedia_manim/__init__.py
yta_multimedia_manim/animations/__init__.py
yta_multimedia_manim/animations/base_manim_animation.py
yta_multimedia_manim/animations/base_manim_animation_wrapper.py
yta_multimedia_manim/animations/base_three_d_manim_animation.py
yta_multimedia_manim/animations/classes/__init__.py
yta_multimedia_manim/animations/classes/image/__init__.py
yta_multimedia_manim/animations/classes/image/opengl_image_mobject.py
yta_multimedia_manim/animations/classes/loading_bar/__init__.py
yta_multimedia_manim/animations/classes/loading_bar/loading_bar_image.py
yta_multimedia_manim/animations/classes/loading_bar/loading_bar_mobject.py
yta_multimedia_manim/animations/classes/loading_bar/loading_bar_with_images_manim_animation.py
yta_multimedia_manim/animations/classes/loading_bar/mobjects/__init__.py
yta_multimedia_manim/animations/classes/loading_bar/mobjects/loading_bar_mobject.py
yta_multimedia_manim/animations/classes/loading_bar/parameter_classes/__init__.py
yta_multimedia_manim/animations/classes/loading_bar/parameter_classes/loading_bar_image.py
yta_multimedia_manim/animations/classes/text/__init__.py
yta_multimedia_manim/animations/classes/text/presets/__init__.py
yta_multimedia_manim/animations/classes/text/presets/magazine_text_is_written_manim_animation.py
yta_multimedia_manim/animations/classes/text/presets/magazine_text_static_manim_animation.py
yta_multimedia_manim/animations/classes/text/presets/rain_of_words_manim_animation.py
yta_multimedia_manim/animations/classes/text/presets/simple_text_manim_animation.py
yta_multimedia_manim/animations/classes/text/presets/test_text_manim_animation.py
yta_multimedia_manim/animations/classes/text/presets/text.py
yta_multimedia_manim/animations/classes/text/presets/text_triplets_manim_animation.py
yta_multimedia_manim/animations/classes/text/presets/text_word_by_word_manim_animation.py
yta_multimedia_manim/animations/classes/three_d/__init__.py
yta_multimedia_manim/animations/classes/three_d/test_3d.py
yta_multimedia_manim-0.0.3.dist-info/LICENSE
yta_multimedia_manim-0.0.3.dist-info/METADATA
yta_multimedia_manim-0.0.3.dist-info/WHEEL
yta_multimedia_manim-0.0.3.dist-info/RECORD
